selenium_python_tools/__init__.py
selenium_python_tools/get_driver.py
selenium_python_tools-0.0.2.dist-info/LICENSE
selenium_python_tools-0.0.2.dist-info/METADATA
selenium_python_tools-0.0.2.dist-info/WHEEL
selenium_python_tools-0.0.2.dist-info/top_level.txt
selenium_python_tools-0.0.2.dist-info/RECORD
